azure/mgmt/deploymentmanager/__init__.py
azure/mgmt/deploymentmanager/_azure_deployment_manager.py
azure/mgmt/deploymentmanager/_configuration.py
azure/mgmt/deploymentmanager/_version.py
azure/mgmt/deploymentmanager/aio/__init__.py
azure/mgmt/deploymentmanager/aio/_azure_deployment_manager.py
azure/mgmt/deploymentmanager/aio/_configuration.py
azure/mgmt/deploymentmanager/aio/operations/__init__.py
azure/mgmt/deploymentmanager/aio/operations/_artifact_sources_operations.py
azure/mgmt/deploymentmanager/aio/operations/_operations.py
azure/mgmt/deploymentmanager/aio/operations/_rollouts_operations.py
azure/mgmt/deploymentmanager/aio/operations/_service_topologies_operations.py
azure/mgmt/deploymentmanager/aio/operations/_service_units_operations.py
azure/mgmt/deploymentmanager/aio/operations/_services_operations.py
azure/mgmt/deploymentmanager/aio/operations/_steps_operations.py
azure/mgmt/deploymentmanager/models/__init__.py
azure/mgmt/deploymentmanager/models/_azure_deployment_manager_enums.py
azure/mgmt/deploymentmanager/models/_models.py
azure/mgmt/deploymentmanager/models/_models_py3.py
azure/mgmt/deploymentmanager/operations/__init__.py
azure/mgmt/deploymentmanager/operations/_artifact_sources_operations.py
azure/mgmt/deploymentmanager/operations/_operations.py
azure/mgmt/deploymentmanager/operations/_rollouts_operations.py
azure/mgmt/deploymentmanager/operations/_service_topologies_operations.py
azure/mgmt/deploymentmanager/operations/_service_units_operations.py
azure/mgmt/deploymentmanager/operations/_services_operations.py
azure/mgmt/deploymentmanager/operations/_steps_operations.py
azure_mgmt_deploymentmanager-1.0.0.dist-info/METADATA
azure_mgmt_deploymentmanager-1.0.0.dist-info/WHEEL
azure_mgmt_deploymentmanager-1.0.0.dist-info/top_level.txt
azure_mgmt_deploymentmanager-1.0.0.dist-info/RECORD
